pdf_to_scan/__init__.py
pdf_to_scan/make_pdfs_look_scanned.py
pdf_to_scan-0.0.3.dist-info/LICENSE
pdf_to_scan-0.0.3.dist-info/METADATA
pdf_to_scan-0.0.3.dist-info/WHEEL
pdf_to_scan-0.0.3.dist-info/entry_points.txt
pdf_to_scan-0.0.3.dist-info/top_level.txt
pdf_to_scan-0.0.3.dist-info/RECORD
