Metadata-Version: 2.1
Name: pdf-to-scan
Version: 0.0.3
Summary: A small script to make your pdfs seem like scanned
Home-page: https://github.com/apurvmishra99/pdf-to-scan
Author: Apurv Mishra
Author-email: me@apurvmishra.com
License: UNKNOWN
Platform: UNKNOWN
Classifier: Programming Language :: Python :: 3
Classifier: License :: OSI Approved :: MIT License
Classifier: Operating System :: OS Independent
Requires-Python: >=3.6
Requires-Dist: Click
Requires-Dist: ghostscript
Requires-Dist: Wand
